better_dedent/__about__.py
better_dedent/__init__.py
better_dedent-0.0.3.dist-info/METADATA
better_dedent-0.0.3.dist-info/WHEEL
better_dedent-0.0.3.dist-info/licenses/LICENSE.txt
better_dedent-0.0.3.dist-info/RECORD
