Metadata-Version: 2.4
Name: better-dedent
Version: 0.0.3
Summary: Basically textwrap.dedent with t-string support.
Project-URL: Documentation, https://github.com/treyhunner/better-dedent#readme
Project-URL: Issues, https://github.com/treyhunner/better-dedent/issues
Project-URL: Source, https://github.com/treyhunner/better-dedent
Author: Trey Hunner
License-Expression: MIT
License-File: LICENSE.txt
Classifier: Development Status :: 4 - Beta
Classifier: Programming Language :: Python
Classifier: Programming Language :: Python :: 3.14
Classifier: Programming Language :: Python :: Implementation :: CPython
Classifier: Programming Language :: Python :: Implementation :: PyPy
Requires-Python: >=3.14
